numeric_notation_parser/__init__.py
numeric_notation_parser/tokenizer.py
numeric_notation_parser-1.0.0.dist-info/METADATA
numeric_notation_parser-1.0.0.dist-info/WHEEL
numeric_notation_parser-1.0.0.dist-info/RECORD
