Metadata-Version: 2.1
Name: numeric_notation_parser
Version: 1.0.0
Summary: Parsing and interpreting notation strings representing numeric sequences, ranges, and individual values. With support for various formats including simple values, range notations (e.g., '10-30'), and stepped ranges (e.g., '0--10/2'), this package simplifies the process of extracting integer values from diverse notation formats. Whether you need to parse input ranges, interpret array indexes, or handle sequence boundaries in your Python applications
License: MIT
Author: Sebastien Nicolet
Author-email: snicolet95@gmail.com
Requires-Python: >=3.11,<4.0
Classifier: License :: OSI Approved :: MIT License
Classifier: Programming Language :: Python :: 3
Classifier: Programming Language :: Python :: 3.11
Classifier: Programming Language :: Python :: 3.12
